pinax/__init__.py
pinax/cohorts/__init__.py
pinax/cohorts/admin.py
pinax/cohorts/apps.py
pinax/cohorts/forms.py
pinax/cohorts/models.py
pinax/cohorts/receivers.py
pinax/cohorts/urls.py
pinax/cohorts/views.py
pinax/cohorts/migrations/0001_initial.py
pinax/cohorts/migrations/__init__.py
pinax/cohorts/tests/__init__.py
pinax/cohorts/tests/tests.py
pinax/cohorts/tests/urls.py
pinax_cohorts-1.0.0.dist-info/AUTHORS
pinax_cohorts-1.0.0.dist-info/LICENSE
pinax_cohorts-1.0.0.dist-info/METADATA
pinax_cohorts-1.0.0.dist-info/WHEEL
pinax_cohorts-1.0.0.dist-info/top_level.txt
pinax_cohorts-1.0.0.dist-info/RECORD
