Metadata-Version: 2.1
Name: pinax-cohorts
Version: 1.0.0
Summary: Create cohorts for inviting people off your pinax-waitinglist waiting list to your private beta site.
Home-page: http://github.com/pinax/pinax-cohorts/
Author: Pinax Team
Author-email: team@pinaxproject.com
License: MIT
Platform: UNKNOWN
Classifier: Development Status :: 4 - Beta
Classifier: Environment :: Web Environment
Classifier: Framework :: Django
Classifier: Framework :: Django :: 2.2
Classifier: Framework :: Django :: 3.0
Classifier: Intended Audience :: Developers
Classifier: License :: OSI Approved :: MIT License
Classifier: Operating System :: OS Independent
Classifier: Programming Language :: Python
Classifier: Programming Language :: Python :: 3.6
Classifier: Programming Language :: Python :: 3.7
Classifier: Programming Language :: Python :: 3.8
Classifier: Topic :: Software Development :: Libraries :: Python Modules
Requires-Dist: django (>=2.2)
Requires-Dist: django-user-accounts (>=2.0.3)
Requires-Dist: pinax-waitinglist (>=2.0.3)
